txk8s/__init__.py
txk8s/_version.py
txk8s/lib.py
txk8s/test/__init__.py
txk8s/test/conftest.py
txk8s/test/test_lib.py
txk8s-0.2.1.dist-info/LICENSE
txk8s-0.2.1.dist-info/METADATA
txk8s-0.2.1.dist-info/WHEEL
txk8s-0.2.1.dist-info/top_level.txt
txk8s-0.2.1.dist-info/RECORD
