Metadata-Version: 2.1
Name: txk8s
Version: 0.2.1
Summary: A Twisted implementation of Kubernetes
Home-page: https://github.com/Brightmd/txk8s
Author: Jessica Grebenschikov
Author-email: jessica@bright.md
License: UNKNOWN
Keywords: twisted,kubernetes
Platform: UNKNOWN
Requires-Dist: future (>=0.16.0)
Requires-Dist: kubernetes (<3.1.0,>=3.0.0)
Requires-Dist: Twisted (<18.0.0,>=16.0.0)
Requires-Dist: PyYAML (<4.0.0,>=3.10)
